dbt_sqlx/__init__.py
dbt_sqlx/cli.py
dbt_sqlx/config.py
dbt_sqlx/dbt_utils.py
dbt_sqlx/support.py
dbt_sqlx/translator.py
dbt_sqlx-1.3.0.dist-info/licenses/LICENSE
dbt_sqlx-1.3.0.dist-info/METADATA
dbt_sqlx-1.3.0.dist-info/WHEEL
dbt_sqlx-1.3.0.dist-info/entry_points.txt
dbt_sqlx-1.3.0.dist-info/top_level.txt
dbt_sqlx-1.3.0.dist-info/RECORD
