Metadata-Version: 2.4
Name: dbt-sqlx
Version: 1.3.0
Summary: CLI for converting DBT SQL models into multiple dialects.
Author-email: Nikhil Suthar <n.suthar.tech@gmail.com>
License-Expression: MIT
Project-URL: repository, https://github.com/NikhilSuthar/dbt-sqlx.git
Project-URL: Documentation, https://github.com/NikhilSuthar/dbt-sqlx/blob/main/README.md
Requires-Python: <3.12,>=3.10.0
License-File: LICENSE
Requires-Dist: langchain<0.4.0,>=0.3.22
Requires-Dist: langchain-openai<0.4.0,>=0.3.11
Requires-Dist: langchain-anthropic<0.4.0,>=0.3.10
Requires-Dist: langchain-google-genai<3.0.0,>=2.1.2
Requires-Dist: langchain-aws<0.3.0,>=0.2.18
Requires-Dist: langchain-mistralai<0.3.0,>=0.2.10
Requires-Dist: langchain-groq<0.4.0,>=0.3.2
Requires-Dist: langchain-ollama<0.4.0,>=0.3.0
Requires-Dist: click<9.0.0,>=8.1.7
Requires-Dist: python-dotenv<2.0.0,>=0.10.2
Requires-Dist: langsmith<0.4.0,>=0.3.20
Dynamic: license-file
